microflow/__init__.py
microflow/event.py
microflow/manager.py
microflow/examples/simple_agent.py
microflow/examples/weather_assistant.py
microflow-0.1.0.dist-info/METADATA
microflow-0.1.0.dist-info/WHEEL
microflow-0.1.0.dist-info/licenses/LICENSE
microflow-0.1.0.dist-info/RECORD
