Metadata-Version: 2.4
Name: microflow
Version: 0.1.0
Summary: A lightweight event-driven workflow system for building AI agents and processing pipelines
Project-URL: Homepage, https://github.com/vikramsoni2/microflow
Project-URL: Bug Tracker, https://github.com/vikramsoni2/microflow/issues
Author-email: Vikram Soni <vikram9880@gmail.com>
License: MIT
License-File: LICENSE
Classifier: Development Status :: 3 - Alpha
Classifier: Intended Audience :: Developers
Classifier: License :: OSI Approved :: MIT License
Classifier: Programming Language :: Python :: 3
Classifier: Programming Language :: Python :: 3.9
Requires-Python: >=3.9
